test_gz_2025/__init__.py
test_gz_2025/common.py
test_gz_2025/test_gz_2025.py
test_gz_2025-0.0.1.dist-info/LICENSE
test_gz_2025-0.0.1.dist-info/METADATA
test_gz_2025-0.0.1.dist-info/WHEEL
test_gz_2025-0.0.1.dist-info/entry_points.txt
test_gz_2025-0.0.1.dist-info/top_level.txt
test_gz_2025-0.0.1.dist-info/RECORD
