Metadata-Version: 2.2
Name: test_gz_2025
Version: 0.0.1
Summary: A python package demo
Author-email: GZ <zhangganchi@sina.com>
License: MIT License
Project-URL: Homepage, https://github.com/batterysnoopy/test_gz_2025
Keywords: test_gz_2025
Classifier: Intended Audience :: Developers
Classifier: License :: OSI Approved :: MIT License
Classifier: Natural Language :: English
Classifier: Programming Language :: Python :: 3.8
Classifier: Programming Language :: Python :: 3.9
Classifier: Programming Language :: Python :: 3.10
Classifier: Programming Language :: Python :: 3.11
Classifier: Programming Language :: Python :: 3.12
Requires-Python: >=3.8
License-File: LICENSE
Requires-Dist: numpy
Provides-Extra: all
Requires-Dist: test_gz_2025[extra]; extra == "all"
Provides-Extra: extra
Requires-Dist: pandas; extra == "extra"
